{
    "pools": [
      {
        "rolls": 1,
        "entries": [
          {
            "type": "minecraft:item",
            "name": "minecraft:emerald",
            "functions": [
              {
                "function": "minecraft:set_nbt",
                "tag": "{display:{Name:'{\"text\":\"Emerald\",\"color\":\"white\",\"italic\":false}',Lore:['{\"text\":\"Valuable\",\"color\":\"yellow\",\"italic\":false}']},rarity:\"valuable\",reap_id:\"emerald\"}"
              }
            ]
          }
        ]
      }
    ]
  }